morpheus/__init__.py
morpheus/main.py
morpheus_integration-0.1.1.dist-info/LICENSE
morpheus_integration-0.1.1.dist-info/METADATA
morpheus_integration-0.1.1.dist-info/WHEEL
morpheus_integration-0.1.1.dist-info/top_level.txt
morpheus_integration-0.1.1.dist-info/RECORD
