Metadata-Version: 2.1
Name: morpheus-integration
Version: 0.1.1
Home-page: https://github.com/StafSis/Morpheus-Python-Integration
Author: Bruno Moretti
License-File: LICENSE
Requires-Dist: requests ; python_version < "3.12"
